bomb/__init__.py
bomb/bomb.py
bomb_boom-1.45.0.dist-info/WHEEL
bomb_boom-1.45.0.dist-info/METADATA
bomb_boom-1.45.0.dist-info/RECORD
