Metadata-Version: 2.1
Name: bomb-boom
Version: 1.45.0
Summary: Bomb package
Author: Nikita Barinov
Author-email: diadorer@yandex.ru
Requires-Python: >=3.9,<4.0
Classifier: Programming Language :: Python :: 3
Classifier: Programming Language :: Python :: 3.9
